iddiff/__init__.py
iddiff/iddiff.py
iddiff-0.0.2.dist-info/LICENSE
iddiff-0.0.2.dist-info/METADATA
iddiff-0.0.2.dist-info/WHEEL
iddiff-0.0.2.dist-info/entry_points.txt
iddiff-0.0.2.dist-info/top_level.txt
iddiff-0.0.2.dist-info/RECORD
