Metadata-Version: 2.1
Name: iddiff
Version: 0.0.2
Summary: Internet-Draft diff tool
Home-page: https://github.com/kesara/iddiff
Author: Kesara Nanayakkara Rathnayake
Author-email: kesara@fq.nz
License: Revised BSD License
Keywords: ietf,rfc,id,internet-draft,diff
Platform: UNKNOWN
Classifier: License :: OSI Approved :: BSD License
Classifier: Programming Language :: Python :: 3
Classifier: Programming Language :: Python :: 3.8
License-File: LICENSE
